dj_vb_conn_pool/__init__.py
dj_vb_conn_pool/backends/__init__.py
dj_vb_conn_pool/backends/vastbase/__init__.py
dj_vb_conn_pool/backends/vastbase/base.py
dj_vb_conn_pool/backends/vastbase/mixins.py
django_vb_connection_pool-0.1.0.dist-info/licenses/LICENSE
django_vb_connection_pool-0.1.0.dist-info/METADATA
django_vb_connection_pool-0.1.0.dist-info/WHEEL
django_vb_connection_pool-0.1.0.dist-info/top_level.txt
django_vb_connection_pool-0.1.0.dist-info/RECORD
