Metadata-Version: 2.4
Name: django-vb-connection-pool
Version: 0.1.0
Summary: vastbase connection pool component library for Django
Author-email: wangxiaoyang <yayaxxww@163.com>
License: MIT License
Project-URL: homepage, https://github.com/yayaxxww/django-vb-connection-pool
Project-URL: repository, https://github.com/yayaxxww/django-vb-connection-pool
Keywords: django,vb,vastbase,persistent,connection,pool,pooling
Classifier: Development Status :: 5 - Production/Stable
Classifier: Environment :: Web Environment
Classifier: Framework :: Django
Classifier: Intended Audience :: Developers
Classifier: License :: OSI Approved :: MIT License
Classifier: Operating System :: OS Independent
Classifier: Programming Language :: Python :: 3
Classifier: Topic :: Software Development :: Libraries :: Python Modules
Requires-Python: >=3.0
License-File: LICENSE
Requires-Dist: django-db-connection-pool
Requires-Dist: django-vastbase-backend
Requires-Dist: SQLAlchemy
Dynamic: license-file
